privex/__init__.py
privex/cspgen/__init__.py
privex/cspgen/__main__.py
privex/cspgen/builder.py
privex/cspgen/cli.py
privex/cspgen/helpers.py
privex/cspgen/version.py
privex/cspgen/examples/example.ini
privex_cspgen-0.5.0.data/scripts/csp-gen
privex_cspgen-0.5.0.data/scripts/cspgen
privex_cspgen-0.5.0.data/scripts/gen-csp
privex_cspgen-0.5.0.dist-info/LICENSE
privex_cspgen-0.5.0.dist-info/LICENSE.txt
privex_cspgen-0.5.0.dist-info/METADATA
privex_cspgen-0.5.0.dist-info/WHEEL
privex_cspgen-0.5.0.dist-info/top_level.txt
privex_cspgen-0.5.0.dist-info/RECORD
