Metadata-Version: 2.1
Name: privex-cspgen
Version: 0.5.0
Summary: A Python tool for generating Content Security Policies without constantly repeating yourself
Home-page: https://github.com/Privex/cspgen
Author: Chris (Someguy123) @ Privex
Author-email: chris@privex.io
License: MIT
Platform: UNKNOWN
Classifier: Programming Language :: Python :: 3
Classifier: Programming Language :: Python :: 3.6
Classifier: Programming Language :: Python :: 3.7
Classifier: Programming Language :: Python :: 3.8
Classifier: Programming Language :: Python :: 3.9
Classifier: License :: OSI Approved :: MIT License
Classifier: Operating System :: POSIX :: Linux
Requires-Dist: privex-helpers (>=3.2.0)
Requires-Dist: privex-loghelper (>1.0.0)
Requires-Dist: rich
Requires-Dist: colorama
